check_number.py
Check_Number-1.0.4.dist-info/LICENSE
Check_Number-1.0.4.dist-info/METADATA
Check_Number-1.0.4.dist-info/WHEEL
Check_Number-1.0.4.dist-info/top_level.txt
Check_Number-1.0.4.dist-info/RECORD
