Metadata-Version: 2.1
Name: Check-Number
Version: 1.0.4
Summary: Number Checker
Home-page: UNKNOWN
Author: Fayas Noushad
License: MIT
Project-URL: Tracker, https://github.com/FayasNoushad/Check-Number/issues
Project-URL: Source, https://github.com/FayasNoushad/Check-Number
Platform: UNKNOWN
Classifier: Intended Audience :: Developers
Classifier: Natural Language :: English
Classifier: Programming Language :: Python
Classifier: License :: OSI Approved :: MIT License
Classifier: Operating System :: OS Independent
Requires-Python: >=3.6
License-File: LICENSE
